AUTHORS.rst
CONTRIBUTING.rst
HISTORY.rst
LICENSE
MANIFEST.in
README.rst
setup.cfg
setup.py
django_fperms_iscore.egg-info/PKG-INFO
django_fperms_iscore.egg-info/SOURCES.txt
django_fperms_iscore.egg-info/dependency_links.txt
django_fperms_iscore.egg-info/not-zip-safe
django_fperms_iscore.egg-info/requires.txt
django_fperms_iscore.egg-info/top_level.txt
fperms_iscore/__init__.py
fperms_iscore/apps.py
fperms_iscore/conf.py
fperms_iscore/enums.py
fperms_iscore/forms.py
fperms_iscore/main.py
fperms_iscore/mixins.py
fperms_iscore/permissions.py
fperms_iscore/locale/cs/LC_MESSAGES/django.mo
fperms_iscore/locale/cs/LC_MESSAGES/django.po
fperms_iscore/management/__init__.py
fperms_iscore/management/commands/__init__.py
fperms_iscore/management/commands/sync_permissions.py