Metadata-Version: 1.1
Name: django-fperms-iscore
Version: 0.2.20
Summary: Perms for iscore library 
Home-page: https://github.com/Formulka/django-fperms-iscore
Author: Petr Olah
Author-email: djangoguru@gmail.com
License: MIT
Download-URL: https://github.com/formulka/django-fperms-iscore/archive/0.2.20.tar.gz
Keywords: django-fperms-iscore
Platform: UNKNOWN
Classifier: Development Status :: 3 - Alpha
Classifier: Framework :: Django
Classifier: Framework :: Django :: 1.11
Classifier: Framework :: Django :: 2.0
Classifier: Intended Audience :: Developers
Classifier: License :: OSI Approved :: BSD License
Classifier: Natural Language :: English
Classifier: Programming Language :: Python :: 3
Classifier: Programming Language :: Python :: 3.5
Classifier: Programming Language :: Python :: 3.6
